Metadata-Version: 2.1
Name: cameo-table
Version: 1.0.0
Summary: add cameo_table.melt(), rename, refactoring
Home-page: https://github.com/bohachu/cameo_table
Author: JC Wang
Author-email: jcxgtcw@gmail.com
License: BSD 2-clause
Platform: UNKNOWN
Classifier: Programming Language :: Python :: 3
